README.md
setup.py
ml_scripts/__init__.py
ml_scripts.egg-info/PKG-INFO
ml_scripts.egg-info/SOURCES.txt
ml_scripts.egg-info/dependency_links.txt
ml_scripts.egg-info/requires.txt
ml_scripts.egg-info/top_level.txt
ml_scripts/model_evaluate/__init__.py
ml_scripts/model_evaluate/classifier_evaluate.py
ml_scripts/model_evaluate/__init__.py
ml_scripts/model_evaluate/classifier_evaluate.py