Metadata-Version: 2.1
Name: ml-scripts
Version: 0.0.3
Summary: Machine Learning Utils
Home-page: https://github.com/zbc0315/ml_scripts
Author: zbc
Author-email: zbc@mail.ustc.edu.cn
Classifier: Programming Language :: Python :: 3
Classifier: License :: OSI Approved :: MIT License
Classifier: Operating System :: OS Independent
Requires-Python: >=3.5
